ethspecify/__init__.py
ethspecify/cli.py
ethspecify/core.py
ethspecify-0.3.7.dist-info/licenses/LICENSE
ethspecify-0.3.7.dist-info/METADATA
ethspecify-0.3.7.dist-info/WHEEL
ethspecify-0.3.7.dist-info/entry_points.txt
ethspecify-0.3.7.dist-info/top_level.txt
ethspecify-0.3.7.dist-info/RECORD
