Metadata-Version: 2.4
Name: ethspecify
Version: 0.3.7
Summary: A utility for processing Ethereum specification tags.
Home-page: https://github.com/jtraglia/ethspecify
Author: Justin Traglia
Author-email: jtraglia@pm.me
Classifier: Programming Language :: Python :: 3
Classifier: License :: OSI Approved :: MIT License
Classifier: Operating System :: OS Independent
Requires-Python: >=3.6
License-File: LICENSE
Requires-Dist: requests==2.32.3
Requires-Dist: PyYAML>=6.0
Dynamic: author
Dynamic: author-email
Dynamic: classifier
Dynamic: description
Dynamic: description-content-type
Dynamic: home-page
Dynamic: license-file
Dynamic: requires-dist
Dynamic: requires-python
Dynamic: summary
